isyntax2raw/__init__.py
isyntax2raw/version.py
isyntax2raw/cli/__init__.py
isyntax2raw/cli/isyntax2raw.py
isyntax2raw/resources/__init__.py
isyntax2raw/resources/ome_template.xml
isyntax2raw-0.6.0.dist-info/LICENSE.txt
isyntax2raw-0.6.0.dist-info/METADATA
isyntax2raw-0.6.0.dist-info/WHEEL
isyntax2raw-0.6.0.dist-info/entry_points.txt
isyntax2raw-0.6.0.dist-info/top_level.txt
isyntax2raw-0.6.0.dist-info/zip-safe
isyntax2raw-0.6.0.dist-info/RECORD
