Metadata-Version: 2.1
Name: isyntax2raw
Version: 0.6.0
Summary: iSyntax to raw format converter
Home-page: https://github.com/glencoesoftware/isyntax2raw
Author: Glencoe Software, Inc.
Author-email: info@glencoesoftware.com
License: License :: OSI Approved :: BSD License
Platform: any
Requires-Python: >=3.6
License-File: LICENSE.txt
Requires-Dist: click ==7.0
Requires-Dist: pillow >=7.1.0
Requires-Dist: numpy ==1.17.3
Requires-Dist: zarr ==2.8.1
Requires-Dist: kajiki ==0.8.2
Requires-Dist: fsspec >=0.9.0
Requires-Dist: python-dateutil >=2.8.2
